regexp_sar/__init__.py
regexp_sar/_regexp_sar_c.pyd
regexp_sar-0.1.2b5.data/headers/sarcore.h
regexp_sar-0.1.2b5.dist-info/LICENSE.txt
regexp_sar-0.1.2b5.dist-info/METADATA
regexp_sar-0.1.2b5.dist-info/WHEEL
regexp_sar-0.1.2b5.dist-info/top_level.txt
regexp_sar-0.1.2b5.dist-info/RECORD
