Metadata-Version: 2.1
Name: regexp-sar
Version: 0.1.2b5
Summary: SAR Regexp Engine for Python
Home-page: https://github.com/nmnsnv/regexp_sar
Author: Noam Nisanov
Author-email: noam.nisanov@gmail.com
License: MIT
Platform: UNKNOWN
Requires-Python: >=3.4
